sqldown/__init__.py
sqldown/__main__.py
sqldown/__version__.py
sqldown/cli.py
sqldown/core.py
sqldown-0.1.0.dist-info/METADATA
sqldown-0.1.0.dist-info/WHEEL
sqldown-0.1.0.dist-info/entry_points.txt
sqldown-0.1.0.dist-info/RECORD
