Metadata-Version: 2.4
Name: sqldown
Version: 0.1.0
Summary: Bidirectional markdown ↔ SQLite conversion with column limit protection
Project-URL: Homepage, https://github.com/mbailey/metool-packages-dev
Project-URL: Repository, https://github.com/mbailey/metool-packages-dev
Project-URL: Issues, https://github.com/mbailey/metool-packages-dev/issues
Author-email: Mike Bailey <mike@bailey.net.au>
License: MIT
Keywords: bidirectional,frontmatter,markdown,sqlite,yaml
Classifier: Development Status :: 4 - Beta
Classifier: Intended Audience :: Developers
Classifier: License :: OSI Approved :: MIT License
Classifier: Programming Language :: Python :: 3
Classifier: Programming Language :: Python :: 3.8
Classifier: Programming Language :: Python :: 3.9
Classifier: Programming Language :: Python :: 3.10
Classifier: Programming Language :: Python :: 3.11
Classifier: Programming Language :: Python :: 3.12
Classifier: Topic :: Database
Classifier: Topic :: Software Development :: Libraries :: Python Modules
Classifier: Topic :: Text Processing :: Markup :: Markdown
Requires-Python: >=3.8
Requires-Dist: click>=8.0
Requires-Dist: pathspec>=0.11
Requires-Dist: pyyaml>=6.0
Requires-Dist: sqlite-utils>=3.30
Requires-Dist: watchdog>=3.0
Provides-Extra: dev
Requires-Dist: pytest-cov; extra == 'dev'
Requires-Dist: pytest>=7.0; extra == 'dev'
